_pydggal.cp37-win_amd64.pyd
dggal/__init__.py
dggal/dggal.py
dggal/bin/dgg.exe
dggal/bin/dgg_wrapper.py
dggal/bin/dggal.dll
dggal/examples/authalic.py
dggal/examples/geom.py
dggal/examples/info.py
dggal/examples/togeo.py
dggal/examples/togeo_json.py
dggal/examples/togeo_text.py
dggal-0.0.6.dist-info/METADATA
dggal-0.0.6.dist-info/WHEEL
dggal-0.0.6.dist-info/entry_points.txt
dggal-0.0.6.dist-info/top_level.txt
dggal-0.0.6.dist-info/RECORD
