Metadata-Version: 2.1
Name: dggal
Version: 0.0.6
Summary: The Discrete Global Grid Abstraction Library (DGGAL)
Home-page: https://dggal.org
Author: Jérôme Jacovella-St-Louis, Ecere Corporation
Author-email: jerome@ecere.com
License: BSD-3-Clause
Keywords: dggs hexagonal-grid global-grid ogc ogc-api gnosis dggrs isea ivea rtea isea3h isea9r ivea3h ivea9r slice-and-dice polyhedral-globe icosahedral rhealpix
Classifier: Development Status :: 4 - Beta
Classifier: Environment :: Console
Classifier: Intended Audience :: Developers
Classifier: Intended Audience :: Science/Research
Classifier: Operating System :: Microsoft :: Windows
Classifier: Operating System :: POSIX :: Linux
Classifier: Operating System :: MacOS
Classifier: Programming Language :: Other
Classifier: Programming Language :: Python :: 3
Classifier: Topic :: Software Development :: Libraries
Classifier: Topic :: Scientific/Engineering :: GIS
Classifier: Topic :: Scientific/Engineering :: Astronomy
Classifier: Topic :: Scientific/Engineering :: Atmospheric Science
Classifier: Topic :: Scientific/Engineering :: Hydrology
Classifier: Topic :: Scientific/Engineering :: Image Processing
Classifier: Topic :: Scientific/Engineering :: Information Analysis
Classifier: Topic :: Scientific/Engineering :: Oceanography
Classifier: Topic :: Scientific/Engineering :: Visualization
Requires-Dist: ecrt >=0.0.5
Requires-Dist: cffi >=1.0.0
